odoo9_addon_partner_contact_height-9.0.1.0.1-py2.7-nspkg.pth
odoo_addons/partner_contact_height/__openerp__.py
odoo_addons/partner_contact_height/__init__.py
odoo_addons/partner_contact_height/README.rst
odoo_addons/partner_contact_height/models/res_partner.py
odoo_addons/partner_contact_height/models/__init__.py
odoo_addons/partner_contact_height/i18n/ja.po
odoo_addons/partner_contact_height/i18n/lv.po
odoo_addons/partner_contact_height/i18n/zh_CN.po
odoo_addons/partner_contact_height/i18n/nb_NO.po
odoo_addons/partner_contact_height/i18n/ru.po
odoo_addons/partner_contact_height/i18n/pt.po
odoo_addons/partner_contact_height/i18n/it.po
odoo_addons/partner_contact_height/i18n/es.po
odoo_addons/partner_contact_height/i18n/nl_BE.po
odoo_addons/partner_contact_height/i18n/ar.po
odoo_addons/partner_contact_height/i18n/lt.po
odoo_addons/partner_contact_height/i18n/ro.po
odoo_addons/partner_contact_height/i18n/tr.po
odoo_addons/partner_contact_height/i18n/mk.po
odoo_addons/partner_contact_height/i18n/hr.po
odoo_addons/partner_contact_height/i18n/bg.po
odoo_addons/partner_contact_height/i18n/es_EC.po
odoo_addons/partner_contact_height/i18n/zh_TW.po
odoo_addons/partner_contact_height/i18n/hu.po
odoo_addons/partner_contact_height/i18n/fr_CA.po
odoo_addons/partner_contact_height/i18n/gl.po
odoo_addons/partner_contact_height/i18n/ca.po
odoo_addons/partner_contact_height/i18n/es_CR.po
odoo_addons/partner_contact_height/i18n/sl.po
odoo_addons/partner_contact_height/i18n/sr@latin.po
odoo_addons/partner_contact_height/i18n/th.po
odoo_addons/partner_contact_height/i18n/cs.po
odoo_addons/partner_contact_height/i18n/pt_PT.po
odoo_addons/partner_contact_height/i18n/nb.po
odoo_addons/partner_contact_height/i18n/da.po
odoo_addons/partner_contact_height/i18n/et.po
odoo_addons/partner_contact_height/i18n/mn.po
odoo_addons/partner_contact_height/i18n/nl.po
odoo_addons/partner_contact_height/i18n/am.po
odoo_addons/partner_contact_height/i18n/de.po
odoo9_addon_partner_contact_height-9.0.1.0.1.dist-info/top_level.txt
odoo9_addon_partner_contact_height-9.0.1.0.1.dist-info/WHEEL
odoo9_addon_partner_contact_height-9.0.1.0.1.dist-info/RECORD
odoo9_addon_partner_contact_height-9.0.1.0.1.dist-info/metadata.json
odoo9_addon_partner_contact_height-9.0.1.0.1.dist-info/DESCRIPTION.rst
odoo9_addon_partner_contact_height-9.0.1.0.1.dist-info/METADATA
odoo9_addon_partner_contact_height-9.0.1.0.1.dist-info/namespace_packages.txt
